rainfallqc/__init__.py
rainfallqc/checks/__init__.py
rainfallqc/checks/comparison_checks.py
rainfallqc/checks/gauge_checks.py
rainfallqc/checks/neighbourhood_checks.py
rainfallqc/checks/pypwsqc_filters.py
rainfallqc/checks/timeseries_checks.py
rainfallqc/core/__init__.py
rainfallqc/core/all_qc_checks.py
rainfallqc/data/__init__.py
rainfallqc/data/ETCCDI/RawData_HADEX2_CDD_1951-2010_ANN_from-90to90_from-180to180.nc
rainfallqc/data/ETCCDI/RawData_HADEX2_CWD_1951-2010_ANN_from-90to90_from-180to180.nc
rainfallqc/data/ETCCDI/RawData_HADEX2_PRCPTOT_1951-2010_ANN_from-90to90_from-180to180.nc
rainfallqc/data/ETCCDI/RawData_HADEX2_R99p_1951-2010_ANN_from-90to90_from-180to180.nc
rainfallqc/data/ETCCDI/RawData_HADEX2_Rx1day_1951-2010_ANN_from-90to90_from-180to180.nc
rainfallqc/data/ETCCDI/RawData_HADEX2_SDII_1951-2010_ANN_from-90to90_from-180to180.nc
rainfallqc/data/ETCCDI/__init__.py
rainfallqc/qc_frameworks/__init__.py
rainfallqc/qc_frameworks/apply_qc_framework.py
rainfallqc/qc_frameworks/inbuilt_qc_frameworks.py
rainfallqc/utils/__init__.py
rainfallqc/utils/data_readers.py
rainfallqc/utils/data_utils.py
rainfallqc/utils/neighbourhood_utils.py
rainfallqc/utils/spatial_utils.py
rainfallqc/utils/stats.py
rainfallqc-0.4.1.dist-info/licenses/LICENSE
rainfallqc-0.4.1.dist-info/WHEEL
rainfallqc-0.4.1.dist-info/METADATA
rainfallqc-0.4.1.dist-info/RECORD
