Metadata-Version: 2.4
Name: rainfallqc
Version: 0.4.1
Summary: Quality control for rainfall data
Author-email: Tom Keel <tomkee@ceh.ac.uk>
Maintainer-email: Tom Keel <tomkee@ceh.ac.uk>
Requires-Python: >=3.10.0
Classifier: Development Status :: 4 - Beta
Classifier: Intended Audience :: Developers
Classifier: Intended Audience :: Science/Research
Classifier: License :: OSI Approved :: GNU General Public License v3 (GPLv3)
Classifier: Natural Language :: English
Classifier: Operating System :: OS Independent
Classifier: Programming Language :: Python :: 3
Classifier: Programming Language :: Python :: 3.10
Classifier: Programming Language :: Python :: 3.11
Classifier: Programming Language :: Python :: 3.12
Classifier: Programming Language :: Python :: 3.13
Classifier: Topic :: Scientific/Engineering :: Hydrology
License-File: LICENSE
Requires-Dist: scipy
Requires-Dist: numpy
Requires-Dist: polars>=1.30
Requires-Dist: pandas
Requires-Dist: pyarrow
Requires-Dist: xarray
Requires-Dist: netCDF4
Requires-Dist: bottleneck
Requires-Dist: geopy
Requires-Dist: poligrain
Requires-Dist: pypwsqc
Requires-Dist: pip ; extra == "dev"
Requires-Dist: numpy ; extra == "dev"
Requires-Dist: bump-my-version ; extra == "dev"
Requires-Dist: ruff ; extra == "dev"
Requires-Dist: black ; extra == "dev"
Requires-Dist: pre_commit ; extra == "dev"
Requires-Dist: pylint ; extra == "dev"
Requires-Dist: pytest ; extra == "dev"
Requires-Dist: pytest-cov ; extra == "dev"
Requires-Dist: matplotlib ; extra == "dev"
Requires-Dist: sphinx ; extra == "dev"
Requires-Dist: sphinx ; extra == "docs"
Requires-Dist: sphinx-copybutton ; extra == "docs"
Requires-Dist: sphinx-rtd-theme ; extra == "docs"
Requires-Dist: mypy ; extra == "lint"
Requires-Dist: ruff ; extra == "lint"
Requires-Dist: pytest ; extra == "test"
Requires-Dist: pytest-cov ; extra == "test"
Project-URL: bugs, https://github.com/thomasjkeel/RainfallQC/issues
Project-URL: changelog, https://github.com/thomasjkeel/RainfallQC/blob/master/changelog.md
Project-URL: homepage, https://github.com/thomasjkeel/RainfallQC
Provides-Extra: dev
Provides-Extra: docs
Provides-Extra: lint
Provides-Extra: test
